elastix_napari/__init__.py
elastix_napari/elastix_registration.py
elastix_napari/napari.yaml
elastix_napari/transformix_widget.py
elastix_napari/tests/__init__.py
elastix_napari/tests/conftest.py
elastix_napari/tests/test_dock_widget.py
elastix_napari/tests/test_registration.py
elastix_napari/tests/test_transformix.py
elastix_napari-0.3.0.dist-info/licenses/LICENSE
elastix_napari-0.3.0.dist-info/METADATA
elastix_napari-0.3.0.dist-info/WHEEL
elastix_napari-0.3.0.dist-info/entry_points.txt
elastix_napari-0.3.0.dist-info/top_level.txt
elastix_napari-0.3.0.dist-info/RECORD
