Metadata-Version: 2.4
Name: elastix-napari
Version: 0.3.0
Summary: A toolbox for rigid and nonrigid registration of images.
Home-page: https://github.com/SuperElastix/elastix-napari
Author: Viktor van der Valk
Author-email: v.o.van_der_valk@lumc.nl
License: Apache Software License 2.0
Project-URL: Project Site, https://elastix.lumc.nl/
Project-URL: Bug Tracker, https://github.com/SuperElastix/elastix-napari/issues
Project-URL: Source Code, https://github.com/SuperElastix/elastix-napari
Project-URL: User Support, https://groups.google.com/g/elastix-imageregistration
Classifier: Development Status :: 4 - Beta
Classifier: Intended Audience :: Developers
Classifier: Framework :: napari
Classifier: Topic :: Software Development :: Testing
Classifier: Programming Language :: Python
Classifier: Programming Language :: Python :: 3
Classifier: Programming Language :: Python :: 3.10
Classifier: Programming Language :: Python :: 3.11
Classifier: Programming Language :: Python :: 3.12
Classifier: Programming Language :: Python :: 3.13
Classifier: Operating System :: OS Independent
Classifier: License :: OSI Approved :: Apache Software License
Requires-Python: >=3.10
License-File: LICENSE
Requires-Dist: itk-elastix>=0.11.1
Requires-Dist: numpy>=1.19.0
Requires-Dist: napari[all]>=0.4.6
Requires-Dist: napari-plugin-engine>=0.1.4
Requires-Dist: magicgui>=0.4.0
Requires-Dist: itk_napari_conversion>=0.5.1
Requires-Dist: napari-itk-io>=0.1.0
Dynamic: author
Dynamic: author-email
Dynamic: classifier
Dynamic: description
Dynamic: description-content-type
Dynamic: home-page
Dynamic: license
Dynamic: license-file
Dynamic: project-url
Dynamic: requires-dist
Dynamic: requires-python
Dynamic: summary
